{
	"meta": {
		"image": "atlas-terrain.png",
		"size": {"w":1290,"h":1032},
		"scale": "1"
	},
	"frames": {
		"arctic-1.png":
		{
			"frame": {"x":1,"y":1,"w":256,"h":256},
			"rotated": false,
			"trimmed": false,
			"spriteSourceSize": {"x":0,"y":0,"w":256,"h":256},
			"sourceSize": {"w":256,"h":256}
		},
		"arctic-2.png":
		{
			"frame": {"x":259,"y":1,"w":256,"h":256},
			"rotated": false,
			"trimmed": false,
			"spriteSourceSize": {"x":0,"y":0,"w":256,"h":256},
			"sourceSize": {"w":256,"h":256}
		},
		"beach.png":
		{
			"frame": {"x":1,"y":259,"w":256,"h":256},
			"rotated": false,
			"trimmed": false,
			"spriteSourceSize": {"x":0,"y":0,"w":256,"h":256},
			"sourceSize": {"w":256,"h":256}
		},
		"deepWater.png":
		{
			"frame": {"x":259,"y":259,"w":256,"h":256},
			"rotated": false,
			"trimmed": false,
			"spriteSourceSize": {"x":0,"y":0,"w":256,"h":256},
			"sourceSize": {"w":256,"h":256}
		},
		"desert2.png":
		{
			"frame": {"x":517,"y":1,"w":256,"h":256},
			"rotated": false,
			"trimmed": false,
			"spriteSourceSize": {"x":0,"y":0,"w":256,"h":256},
			"sourceSize": {"w":256,"h":256}
		},
		"savanna-3.png":
		{
			"frame": {"x":517,"y":259,"w":256,"h":256},
			"rotated": false,
			"trimmed": false,
			"spriteSourceSize": {"x":0,"y":0,"w":256,"h":256},
			"sourceSize": {"w":256,"h":256}
		},
		"savanna1.png":
		{
			"frame": {"x":1,"y":517,"w":256,"h":256},
			"rotated": false,
			"trimmed": false,
			"spriteSourceSize": {"x":0,"y":0,"w":256,"h":256},
			"sourceSize": {"w":256,"h":256}
		},
		"temperate.png":
		{
			"frame": {"x":259,"y":517,"w":256,"h":256},
			"rotated": false,
			"trimmed": false,
			"spriteSourceSize": {"x":0,"y":0,"w":256,"h":256},
			"sourceSize": {"w":256,"h":256}
		},
		"tropical-2.png":
		{
			"frame": {"x":517,"y":517,"w":256,"h":256},
			"rotated": false,
			"trimmed": false,
			"spriteSourceSize": {"x":0,"y":0,"w":256,"h":256},
			"sourceSize": {"w":256,"h":256}
		},
		"tropical-hills-6.png":
		{
			"frame": {"x":775,"y":1,"w":256,"h":256},
			"rotated": false,
			"trimmed": false,
			"spriteSourceSize": {"x":0,"y":0,"w":256,"h":256},
			"sourceSize": {"w":256,"h":256}
		},
		"tropical-hills-7.png":
		{
			"frame": {"x":775,"y":259,"w":256,"h":256},
			"rotated": false,
			"trimmed": false,
			"spriteSourceSize": {"x":0,"y":0,"w":256,"h":256},
			"sourceSize": {"w":256,"h":256}
		},
		"tundra-1.png":
		{
			"frame": {"x":775,"y":517,"w":256,"h":256},
			"rotated": false,
			"trimmed": false,
			"spriteSourceSize": {"x":0,"y":0,"w":256,"h":256},
			"sourceSize": {"w":256,"h":256}
		},
		"tundra-3.png":
		{
			"frame": {"x":1,"y":775,"w":256,"h":256},
			"rotated": false,
			"trimmed": false,
			"spriteSourceSize": {"x":0,"y":0,"w":256,"h":256},
			"sourceSize": {"w":256,"h":256}
		},
		"water.png":
		{
			"frame": {"x":259,"y":775,"w":256,"h":256},
			"rotated": false,
			"trimmed": false,
			"spriteSourceSize": {"x":0,"y":0,"w":256,"h":256},
			"sourceSize": {"w":256,"h":256}
		},
		"whitenoise.png":
		{
			"frame": {"x":517,"y":775,"w":256,"h":256},
			"rotated": false,
			"trimmed": false,
			"spriteSourceSize": {"x":0,"y":0,"w":256,"h":256},
			"sourceSize": {"w":256,"h":256}
		},
		"hill-arctic-1.png":
		{
			"frame": {"x":775,"y":775,"w":256,"h":145},
			"rotated": false,
			"trimmed": false,
			"spriteSourceSize": {"x":0,"y":0,"w":256,"h":145},
			"sourceSize": {"w":256,"h":145}
		},
		"hill-desert-1.png":
		{
			"frame": {"x":1033,"y":1,"w":256,"h":138},
			"rotated": false,
			"trimmed": false,
			"spriteSourceSize": {"x":0,"y":0,"w":256,"h":138},
			"sourceSize": {"w":256,"h":138}
		},
		"hill-savanna-1.png":
		{
			"frame": {"x":1033,"y":141,"w":256,"h":138},
			"rotated": false,
			"trimmed": false,
			"spriteSourceSize": {"x":0,"y":0,"w":256,"h":138},
			"sourceSize": {"w":256,"h":138}
		},
		"hill-temperate-1.png":
		{
			"frame": {"x":1033,"y":281,"w":256,"h":138},
			"rotated": false,
			"trimmed": false,
			"spriteSourceSize": {"x":0,"y":0,"w":256,"h":138},
			"sourceSize": {"w":256,"h":138}
		},
		"hill-tropical-1.png":
		{
			"frame": {"x":1033,"y":421,"w":256,"h":138},
			"rotated": false,
			"trimmed": false,
			"spriteSourceSize": {"x":0,"y":0,"w":256,"h":138},
			"sourceSize": {"w":256,"h":138}
		},
		"hill-tundra-1.png":
		{
			"frame": {"x":1033,"y":561,"w":256,"h":138},
			"rotated": false,
			"trimmed": false,
			"spriteSourceSize": {"x":0,"y":0,"w":256,"h":138},
			"sourceSize": {"w":256,"h":138}
		}
	}
}